py_secure_edge/__init__.py
py_secure_edge/custom_token.py
py_secure_edge-0.0.2.dist-info/METADATA
py_secure_edge-0.0.2.dist-info/WHEEL
py_secure_edge-0.0.2.dist-info/top_level.txt
py_secure_edge-0.0.2.dist-info/RECORD
