Metadata-Version: 2.1
Name: py-secure-edge
Version: 0.0.2
Summary: secure edge token generator
Author-email: Arief Hidayat <mr.arief.hidayat@gmail.com>
Project-URL: Homepage, https://github.com/arief-hidayat/py-token-generator
Project-URL: Bug Tracker, https://github.com/arief-hidayat/py-token-generator/issues
Classifier: Programming Language :: Python :: 3
Classifier: License :: OSI Approved :: MIT License
Classifier: Operating System :: OS Independent
Requires-Python: >=3.7
Requires-Dist: pyjwt ==2.8.0
Requires-Dist: ksuid ==1.3
